debounce.v
`timescale 1ns / 1ns

module debounce #(parameter DEL = 50) (input clk_i, rst_i, btn_i, output btn_o);
    integer counter;

    reg btn_state;

    assign btn_o = btn_state;

    always @(posedge clk_i, posedge rst_i) begin
        if(rst_i) begin
            counter <= 0;
            btn_state <= 0;
        end
        else if(clk_i && (!btn_state) && btn_i) begin
            btn_state <= 1;
        end
        else if(clk_i) begin
            if(btn_state && counter < DEL) begin
                counter <= counter + 1;
            end
            else begin
                counter <= 0;
                btn_state <= 0;
            end
        end
    end

endmodule

debounce_tb.v
`timescale 1ns / 1ns
`include "debounce.v"

module debounce_tb;
    reg clk_i, rst_i, btn_i;
    
    wire btn_o;

    debounce  #(50) uut(clk_i, rst_i, btn_i, btn_o);

    initial begin
        $dumpfile("debounce.vcd");
        $dumpvars(0, clk_i, rst_i, btn_i, btn_o);

        #0 rst_i = 0;
        #0 btn_i = 0;
        #0 clk_i = 0;

        #1 rst_i = 1;
        #1 rst_i = 0;

        #10 btn_i = 1;
        #10 btn_i = 0;
        #20 btn_i = 1;
        #5  btn_i = 0;

        #100 $finish;
    end

    always #1 clk_i <= ~clk_i;
endmodule

debounce.vcd
$date
	Tue Mar 12 17:23:14 2024
$end
$version
	Icarus Verilog
$end
$timescale
	1ns
$end
$scope module debounce_tb $end
$var reg 1 ! clk_i $end
$upscope $end
$scope module debounce_tb $end
$var reg 1 " rst_i $end
$upscope $end
$scope module debounce_tb $end
$var reg 1 # btn_i $end
$upscope $end
$scope module debounce_tb $end
$var wire 1 $ btn_o $end
$upscope $end
$enddefinitions $end
$comment Show the parameter values. $end
$dumpall
$end
#0
$dumpvars
x$
0#
0"
0!
$end
#1
0$
1!
1"
#2
0!
0"
#3
1!
#4
0!
#5
1!
#6
0!
#7
1!
#8
0!
#9
1!
#10
0!
#11
1!
#12
0!
1#
#13
1$
1!
#14
0!
#15
1!
#16
0!
#17
1!
#18
0!
#19
1!
#20
0!
#21
1!
#22
0!
0#
#23
1!
#24
0!
#25
1!
#26
0!
#27
1!
#28
0!
#29
1!
#30
0!
#31
1!
#32
0!
#33
1!
#34
0!
#35
1!
#36
0!
#37
1!
#38
0!
#39
1!
#40
0!
#41
1!
#42
0!
1#
#43
1!
#44
0!
#45
1!
#46
0!
#47
1!
0#
