div.v
`timescale 1ns / 1ns

module div #(parameter NDIV = 3)(
    input clk_i,
    input rst_i,
    output reg clk_o
);

integer counter = 0;

always @(posedge clk_i, posedge rst_i) begin
    if(rst_i) begin
        counter <= 0;
        clk_o <= 0;
    end
    else if(clk_i) begin
        counter <= counter + 1;
        if(counter == NDIV/2) begin
            clk_o = 1;
        end
        else if(counter == NDIV - 1) begin
            counter <= 0;
            clk_o <= 0;    
        end
    end
end
    
endmodule

display.v
`timescale 1ns / 1ns

module display(input clk_i, input rst_i, input [5:0] hour_i, input [5:0] min_i, output reg [7:0] led7_seg_o, output reg [7:0] led7_an_o);
    function [7:0] seg_char;
        input [3:0] data;
        begin
            case (data)
                4'b0000 : seg_char = 8'b0000_0011;   // 0
                4'b0001 : seg_char = 8'b1001_1111;   // 1
                4'b0010 : seg_char = 8'b0010_0101;   // 2
                4'b0011 : seg_char = 8'b0000_1101;   // 3
                4'b0100 : seg_char = 8'b1001_1001;   // 4
                4'b0101 : seg_char = 8'b0100_1001;   // 5
                4'b0110 : seg_char = 8'b0100_0001;   // 6
                4'b0111 : seg_char = 8'b0001_1111;   // 7
                4'b1000 : seg_char = 8'b0000_0001;   // 8
                4'b1001 : seg_char = 8'b0000_1001;   // 9
                4'b1010 : seg_char = 8'b0001_0001;   // A
                4'b1011 : seg_char = 8'b1100_0001;   // B
                4'b1100 : seg_char = 8'b0110_0011;   // C
                4'b1101 : seg_char = 8'b1000_0101;   // D
                4'b1110 : seg_char = 8'b0110_0001;   // E
                4'b1111 : seg_char = 8'b0111_0001;   // F
                default : seg_char = 8'b1111_1111;   // *blank*
            endcase
        end
    endfunction

    reg [2:0] digit;
    
    always @(posedge clk_i, posedge rst_i) begin
        if(rst_i) begin
            digit <= 0;
            led7_seg_o <= 8'b11111111;
            led7_an_o <= 8'b11111110;
        end
        else if(clk_i) begin
            if(digit >= 7)
                digit <= 0;
            else
                digit <= digit + 1;

            led7_an_o <= ~(1 << digit);

            case(digit)
                0: led7_seg_o <= seg_char(min_i % 10);
                1: led7_seg_o <= seg_char(min_i / 10);
                2: led7_seg_o <= 8'b11111110;
                3: led7_seg_o <= seg_char(hour_i % 10);
                4: led7_seg_o <= seg_char(hour_i / 10);
                5: led7_seg_o <= 8'b11111111;
                6: led7_seg_o <= 8'b11111111;
                7: led7_seg_o <= 8'b11111111;
            endcase
        end
    end
endmodule

debounce.v
`timescale 1ns / 1ns

module debounce #(parameter DEL = 50) (input clk_i, rst_i, btn_i, output btn_o);
    integer counter;

    reg btn_state;

    assign btn_o = btn_state;

    always @(posedge clk_i, posedge rst_i) begin
        if(rst_i) begin
            counter <= 0;
            btn_state <= 0;
        end
        else if(clk_i && (!btn_state) && btn_i) begin
            btn_state <= 1;
        end
        else if(clk_i) begin
            if(btn_state && counter < DEL) begin
                counter <= counter + 1;
            end
            else begin
                counter <= 0;
                btn_state <= 0;
            end
        end
    end

endmodule

top.v
`timescale 1ns / 1ns
`include "debounce.v"
`include "div.v"
`include "display.v"

module top #(parameter TPS = 10) (input clk_i, input btnl_i, input btnr_i, input btnu_i,  input rst_i, output [7:0] led7_seg_o, output [7:0] led7_an_o);
    wire inc_hour, inc_minute, speedup;
    debounce #(50) l_db(clk_i, rst_i, btnl_i, inc_hour);
    debounce #(50) r_db(clk_i, rst_i, btnr_i, inc_minute);
    debounce #(50) u_db(clk_i, rst_i, btnu_i, speedup);

    reg [5:0] h_val, m_val, s_val;

    display disp(clk_i, rst_i, h_val, m_val, led7_seg_o, led7_an_o);

    integer tick_counter;

    initial $dumpvars(0, h_val, m_val, s_val);

    always @(posedge rst_i) begin
        if(rst_i) begin
            h_val <= 0;
            m_val <= 0;
            s_val <= 0;

            tick_counter <= 0;
        end
    end

    always @(posedge clk_i) begin
        if(tick_counter >= (speedup ? 1 : TPS - 1)) begin
            tick_counter <= 0;

            if(s_val >= 59) begin
                s_val <= 0;
                m_val <= m_val + 1;
            end
            else begin
                s_val <= s_val + 1;
            end

            if(m_val >= 59 && s_val >= 59) begin
                m_val <= 0;
                h_val <= h_val + 1;
            end

            if(h_val >= 23 && m_val >= 59 && s_val >= 59) begin
                h_val <= 0;
                m_val <= 0;
                s_val <= 0;
            end
        end
        else begin
            tick_counter <= tick_counter + 1;

            if(tick_counter % (TPS / 5) == 0 && btnl_i == 1) begin
                if(h_val < 23)
                    h_val <= h_val + 1;
                else
                    h_val <= 0;
            end

            if(tick_counter % (TPS / 5) == 0 && btnr_i == 1) begin
                if(m_val < 59)
                    m_val <= m_val + 1;
                else
                    m_val <= 0;
            end
        end
    end

endmodule

top_tb.v
`timescale 1ns / 1ns
`include "top.v"

module top_tb;
    reg clk_i, rst_i;
    reg btnl_i, btnr_i, btnu_i;

    wire [7:0] led7_seg_o, led7_an_o;

    top #(100) rtc(clk_i, btnl_i, btnr_i, btnu_i, rst_i, led7_seg_o, led7_an_o);

    initial begin
        $dumpfile("top.vcd");
        $dumpvars(0, clk_i, btnl_i, btnr_i, btnu_i, rst_i, led7_seg_o, led7_an_o);

        #0 rst_i = 0;
        #0 clk_i = 0;
        #0 btnl_i = 0;
        #0 btnr_i = 0;
        #0 btnu_i = 0;

        #1 rst_i = 1;
        #1 rst_i = 0;

        #1000 btnr_i = 1;
        #1010 btnr_i = 0;

        #2000 btnl_i = 1;
        #2010 btnl_i = 0;

        #3000 btnu_i = 1;
        #3010 btnu_i = 0;

        #100000 $finish;
    end

    always #1 clk_i <= ~clk_i;
endmodule

dump.vcd
$date
	Wed Mar 13 00:14:11 2024
$end
$version
	Icarus Verilog
$end
$timescale
	1ns
$end
$scope module top_tb $end
$scope module rtc $end
$var reg 6 ! h_val [5:0] $end
$upscope $end
$upscope $end
$scope module top_tb $end
$scope module rtc $end
$var reg 6 " m_val [5:0] $end
$upscope $end
$upscope $end
$scope module top_tb $end
$scope module rtc $end
$var reg 6 # s_val [5:0] $end
$upscope $end
$upscope $end
$scope module top_tb $end
$var reg 1 $ clk_i $end
$upscope $end
$scope module top_tb $end
$var reg 1 % btnl_i $end
$upscope $end
$scope module top_tb $end
$var reg 1 & btnr_i $end
$upscope $end
$scope module top_tb $end
$var reg 1 ' btnu_i $end
$upscope $end
$scope module top_tb $end
$var reg 1 ( rst_i $end
$upscope $end
$scope module top_tb $end
$var wire 8 ) led7_seg_o [7:0] $end
$upscope $end
$scope module top_tb $end
$var wire 8 * led7_an_o [7:0] $end
$upscope $end
$enddefinitions $end
$comment Show the parameter values. $end
$dumpall
$end
#0
$dumpvars
bx *
bx )
0(
0'
0&
0%
0$
bx #
bx "
bx !
$end
#1
b11111110 *
b11111111 )
b0 #
b0 "
b0 !
1$
1(
#2
0$
0(
#3
b11 )
1$
#4
0$
#5
b11111101 *
1$
#6
0$
#7
b11111110 )
b11111011 *
1$
#8
0$
#9
b11 )
b11110111 *
1$
#10
0$
#11
b11101111 *
1$
#12
0$
#13
b11111111 )
b11011111 *
1$
#14
0$
#15
b10111111 *
1$
#16
0$
#17
b1111111 *
1$
#18
0$
#19
b11 )
b11111110 *
1$
#20
0$
#21
b11111101 *
1$
#22
0$
#23
b11111110 )
b11111011 *
1$
#24
0$
#25
b11 )
b11110111 *
1$
#26
0$
#27
b11101111 *
1$
#28
0$
#29
b11111111 )
b11011111 *
1$
#30
0$
#31
b10111111 *
1$
#32
0$
#33
b1111111 *
1$
#34
0$
#35
b11 )
b11111110 *
1$
#36
0$
#37
b11111101 *
1$
#38
0$
#39
b11111110 )
b11111011 *
1$
#40
0$
#41
b11 )
b11110111 *
1$
#42
0$
#43
b11101111 *
1$
#44
0$
#45
b11111111 )
b11011111 *
1$
#46
0$
#47
b10111111 *
1$
#48
0$
#49
b1111111 *
1$
#50
0$
#51
b11 )
b11111110 *
1$
#52
0$
#53
b11111101 *
1$
#54
0$
#55
b11111110 )
b11111011 *
1$
#56
0$
#57
b11 )
b11110111 *
1$
#58
0$
#59
b11101111 *
1$
#60
0$
#61
b11111111 )
b11011111 *
1$
#62
0$
#63
b10111111 *
1$
#64
0$
#65
b1111111 *
1$
#66
0$
#67
b11 )
b11111110 *
1$
#68
0$
#69
b11111101 *
1$
#70
0$
#71
b11111110 )
b11111011 *
1$
#72
0$
#73
b11 )
b11110111 *
1$
#74
0$
#75
b11101111 *
1$
#76
0$
#77
b11111111 )
b11011111 *
1$
#78
0$
#79
b10111111 *
1$
#80
0$
#81
b1111111 *
1$
#82
0$
#83
b11 )
b11111110 *
1$
#84
0$
#85
b11111101 *
1$
#86
0$
#87
b11111110 )
b11111011 *
1$
#88
0$
#89
b11 )
b11110111 *
1$
#90
0$
#91
b11101111 *
1$
#92
0$
#93
b11111111 )
b11011111 *
1$
#94
0$
#95
b10111111 *
1$
#96
0$
#97
b1111111 *
1$
#98
0$
#99
b11 )
b11111110 *
1$
#100
0$
#101
b11111101 *
1$
#102
0$
#103
b11111110 )
b11111011 *
1$
#104
0$
#105
b11 )
b11110111 *
1$
#106
0$
#107
b11101111 *
1$
#108
0$
#109
b11111111 )
b11011111 *
1$
#110
0$
#111
b10111111 *
1$
#112
0$
#113
b1111111 *
1$
#114
0$
#115
b11 )
b11111110 *
1$
#116
0$
#117
b11111101 *
1$
#118
0$
#119
b11111110 )
b11111011 *
1$
#120
0$
#121
b11 )
b11110111 *
1$
#122
0$
#123
b11101111 *
1$
#124
0$
#125
b11111111 )
b11011111 *
1$
#126
0$
#127
b10111111 *
1$
#128
0$
#129
b1111111 *
1$
#130
0$
#131
b11 )
b11111110 *
1$
#132
0$
#133
b11111101 *
1$
#134
0$
#135
b11111110 )
b11111011 *
1$
#136
0$
#137
b11 )
b11110111 *
1$
#138
0$
#139
b11101111 *
1$
#140
0$
#141
b11111111 )
b11011111 *
1$
#142
0$
#143
b10111111 *
1$
#144
0$
#145
b1111111 *
1$
#146
0$
#147
b11 )
b11111110 *
1$
#148
0$
#149
b11111101 *
1$
#150
0$
#151
b11111110 )
b11111011 *
1$
#152
0$
#153
b11 )
b11110111 *
1$
#154
0$
#155
b11101111 *
1$
#156
0$
#157
b11111111 )
b11011111 *
1$
#158
0$
#159
b10111111 *
1$
#160
0$
#161
b1111111 *
1$
#162
0$
#163
b11 )
b11111110 *
1$
#164
0$
#165
b11111101 *
1$
#166
0$
#167
b11111110 )
b11111011 *
1$
#168
0$
#169
b11 )
b11110111 *
1$
#170
0$
#171
b11101111 *
1$
#172
0$
#173
b11111111 )
b11011111 *
1$
#174
0$
#175
b10111111 *
1$
#176
0$
#177
b1111111 *
1$
#178
0$
#179
b11 )
b11111110 *
1$
#180
0$
#181
b11111101 *
1$
#182
0$
#183
b11111110 )
b11111011 *
1$
#184
0$
#185
b11 )
b11110111 *
1$
#186
0$
#187
b11101111 *
1$
#188
0$
#189
b11111111 )
b11011111 *
1$
#190
0$
#191
b10111111 *
1$
#192
0$
#193
b1111111 *
1$
#194
0$
#195
b11 )
b11111110 *
1$
#196
0$
#197
b11111101 *
1$
#198
0$
#199
b11111110 )
b11111011 *
b1 #
1$
#200
0$
#201
b11 )
b11110111 *
1$
#202
0$
#203
b11101111 *
1$
#204
0$
#205
b11111111 )
b11011111 *
1$
#206
0$
#207
b10111111 *
1$
#208
0$
#209
b1111111 *
1$
#210
0$
#211
b11 )
b11111110 *
1$
#212
0$
#213
b11111101 *
1$
#214
0$
#215
b11111110 )
b11111011 *
1$
#216
0$
#217
b11 )
b11110111 *
1$
#218
0$
#219
b11101111 *
1$
#220
0$
#221
b11111111 )
b11011111 *
1$
#222
0$
#223
b10111111 *
1$
#224
0$
#225
b1111111 *
1$
#226
0$
#227
b11 )
b11111110 *
1$
#228
0$
#229
b11111101 *
1$
#230
0$
#231
b11111110 )
b11111011 *
1$
#232
0$
#233
b11 )
b11110111 *
1$
#234
0$
#235
b11101111 *
1$
#236
0$
#237
b11111111 )
b11011111 *
1$
#238
0$
#239
b10111111 *
1$
#240
0$
#241
b1111111 *
1$
#242
0$
#243
b11 )
b11111110 *
1$
#244
0$
#245
b11111101 *
1$
#246
0$
#247
b11111110 )
b11111011 *
1$
#248
0$
#249
b11 )
b11110111 *
1$
#250
0$
#251
b11101111 *
1$
#252
0$
#253
b11111111 )
b11011111 *
1$
#254
0$
#255
b10111111 *
1$
#256
0$
#257
b1111111 *
1$
#258
0$
#259
b11 )
b11111110 *
1$
#260
0$
#261
b11111101 *
1$
#262
0$
#263
b11111110 )
b11111011 *
1$
#264
0$
#265
b11 )
b11110111 *
1$
#266
0$
#267
b11101111 *
1$
#268
0$
#269
b11111111 )
b11011111 *
1$
#270
0$
#271
b10111111 *
1$
#272
0$
#273
b1111111 *
1$
#274
0$
#275
b11 )
b11111110 *
1$
#276
0$
#277
b11111101 *
1$
#278
0$
#279
b11111110 )
b11111011 *
1$
#280
0$
#281
b11 )
b11110111 *
1$
#282
0$
#283
b11101111 *
1$
#284
0$
#285
b11111111 )
b11011111 *
1$
#286
0$
#287
b10111111 *
1$
#288
0$
#289
b1111111 *
1$
#290
0$
#291
b11 )
b11111110 *
1$
#292
0$
#293
b11111101 *
1$
#294
0$
#295
b11111110 )
b11111011 *
1$
#296
0$
#297
b11 )
b11110111 *
1$
#298
0$
#299
b11101111 *
1$
#300
0$
#301
b11111111 )
b11011111 *
1$
#302
0$
#303
b10111111 *
1$
#304
0$
#305
b1111111 *
1$
#306
0$
#307
b11 )
b11111110 *
1$
#308
0$
#309
b11111101 *
1$
#310
0$
#311
b11111110 )
b11111011 *
1$
#312
0$
#313
b11 )
b11110111 *
1$
#314
0$
#315
b11101111 *
1$
#316
0$
#317
b11111111 )
b11011111 *
1$
#318
0$
#319
b10111111 *
1$
#320
0$
#321
b1111111 *
1$
#322
0$
#323
b11 )
b11111110 *
1$
#324
0$
#325
b11111101 *
1$
#326
0$
#327
b11111110 )
b11111011 *
1$
#328
0$
#329
b11 )
b11110111 *
1$
#330
0$
#331
b11101111 *
1$
#332
0$
#333
b11111111 )
b11011111 *
1$
#334
0$
#335
b10111111 *
1$
#336
0$
#337
b1111111 *
1$
#338
0$
#339
b11 )
b11111110 *
1$
#340
0$
#341
b11111101 *
1$
#342
0$
#343
b11111110 )
b11111011 *
1$
#344
0$
#345
b11 )
b11110111 *
1$
#346
0$
#347
b11101111 *
1$
#348
0$
#349
b11111111 )
b11011111 *
1$
#350
0$
#351
b10111111 *
1$
#352
0$
#353
b1111111 *
1$
#354
0$
#355
b11 )
b11111110 *
1$
#356
0$
#357
b11111101 *
1$
#358
0$
#359
b11111110 )
b11111011 *
1$
#360
0$
#361
b11 )
b11110111 *
1$
#362
0$
#363
b11101111 *
1$
#364
0$
#365
b11111111 )
b11011111 *
1$
#366
0$
#367
b10111111 *
1$
#368
0$
#369
b1111111 *
1$
#370
0$
#371
b11 )
b11111110 *
1$
#372
0$
#373
b11111101 *
1$
#374
0$
#375
b11111110 )
b11111011 *
1$
#376
0$
#377
b11 )
b11110111 *
1$
#378
0$
#379
b11101111 *
1$
#380
0$
#381
b11111111 )
b11011111 *
1$
#382
0$
#383
b10111111 *
1$
#384
0$
#385
b1111111 *
1$
#386
0$
#387
b11 )
b11111110 *
1$
#388
0$
#389
b11111101 *
1$
#390
0$
#391
b11111110 )
b11111011 *
1$
#392
0$
#393
b11 )
b11110111 *
1$
#394
0$
#395
b11101111 *
1$
#396
0$
#397
b11111111 )
b11011111 *
1$
#398
0$
#399
b10111111 *
b10 #
1$
#400
0$
#401
b1111111 *
1$
#402
0$
#403
b11 )
b11111110 *
1$
#404
0$
#405
b11111101 *
1$
#406
0$
#407
b11111110 )
b11111011 *
1$
#408
0$
#409
b11 )
b11110111 *
1$
#410
0$
#411
b11101111 *
1$
#412
0$
#413
b11111111 )
b11011111 *
1$
#414
0$
#415
b10111111 *
1$
#416
0$
#417
b1111111 *
1$
#418
0$
#419
b11 )
b11111110 *
1$
#420
0$
#421
b11111101 *
1$
#422
0$
#423
b11111110 )
b11111011 *
1$
#424
0$
#425
b11 )
b11110111 *
1$
#426
0$
#427
b11101111 *
1$
#428
0$
#429
b11111111 )
b11011111 *
1$
#430
0$
#431
b10111111 *
1$
#432
0$
#433
b1111111 *
1$
#434
0$
#435
b11 )
b11111110 *
1$
#436
0$
#437
b11111101 *
1$
#438
0$
#439
b11111110 )
b11111011 *
1$
#440
0$
#441
b11 )
b11110111 *
1$
#442
0$
#443
b11101111 *
1$
#444
0$
#445
b11111111 )
b11011111 *
1$
#446
0$
#447
b10111111 *
1$
#448
0$
#449
b1111111 *
1$
#450
0$
#451
b11 )
b11111110 *
1$
#452
0$
#453
b11111101 *
1$
#454
0$
#455
b11111110 )
b11111011 *
1$
#456
0$
#457
b11 )
b11110111 *
1$
#458
0$
#459
b11101111 *
1$
#460
0$
#461
b11111111 )
b11011111 *
1$
#462
0$
#463
b10111111 *
1$
#464
0$
#465
b1111111 *
1$
#466
0$
#467
b11 )
b11111110 *
1$
#468
0$
#469
b11111101 *
1$
#470
0$
#471
b11111110 )
b11111011 *
1$
#472
0$
#473
b11 )
b11110111 *
1$
#474
0$
#475
b11101111 *
1$
#476
0$
#477
b11111111 )
b11011111 *
1$
#478
0$
#479
b10111111 *
1$
#480
0$
#481
b1111111 *
1$
#482
0$
#483
b11 )
b11111110 *
1$
#484
0$
#485
b11111101 *
1$
#486
0$
#487
b11111110 )
b11111011 *
1$
#488
0$
#489
b11 )
b11110111 *
1$
#490
0$
#491
b11101111 *
1$
#492
0$
#493
b11111111 )
b11011111 *
1$
#494
0$
#495
b10111111 *
1$
#496
0$
#497
b1111111 *
1$
#498
0$
#499
b11 )
b11111110 *
1$
#500
0$
#501
b11111101 *
1$
#502
0$
#503
b11111110 )
b11111011 *
1$
#504
0$
#505
b11 )
b11110111 *
1$
#506
0$
#507
b11101111 *
1$
#508
0$
#509
b11111111 )
b11011111 *
1$
#510
0$
#511
b10111111 *
1$
#512
0$
#513
b1111111 *
1$
#514
0$
#515
b11 )
b11111110 *
1$
#516
0$
#517
b11111101 *
1$
#518
0$
#519
b11111110 )
b11111011 *
1$
#520
0$
#521
b11 )
b11110111 *
1$
#522
0$
#523
b11101111 *
1$
#524
0$
#525
b11111111 )
b11011111 *
1$
#526
0$
#527
b10111111 *
1$
#528
0$
#529
b1111111 *
1$
#530
0$
#531
b11 )
b11111110 *
1$
#532
0$
#533
b11111101 *
1$
#534
0$
#535
b11111110 )
b11111011 *
1$
#536
0$
#537
b11 )
b11110111 *
1$
#538
0$
#539
b11101111 *
1$
#540
0$
#541
b11111111 )
b11011111 *
1$
#542
0$
#543
b10111111 *
1$
#544
0$
#545
b1111111 *
1$
#546
0$
#547
b11 )
b11111110 *
1$
#548
0$
#549
b11111101 *
1$
#550
0$
#551
b11111110 )
b11111011 *
1$
#552
0$
#553
b11 )
b11110111 *
1$
#554
0$
#555
b11101111 *
1$
#556
0$
#557
b11111111 )
b11011111 *
1$
#558
0$
#559
b10111111 *
1$
#560
0$
#561
b1111111 *
1$
#562
0$
#563
b11 )
b11111110 *
1$
#564
0$
#565
b11111101 *
1$
#566
0$
#567
b11111110 )
b11111011 *
1$
#568
0$
#569
b11 )
b11110111 *
1$
#570
0$
#571
b11101111 *
1$
#572
0$
#573
b11111111 )
b11011111 *
1$
#574
0$
#575
b10111111 *
1$
#576
0$
#577
b1111111 *
1$
#578
0$
#579
b11 )
b11111110 *
1$
#580
0$
#581
b11111101 *
1$
#582
0$
#583
b11111110 )
b11111011 *
1$
#584
0$
#585
b11 )
b11110111 *
1$
#586
0$
#587
b11101111 *
1$
#588
0$
#589
b11111111 )
b11011111 *
1$
#590
0$
#591
b10111111 *
1$
#592
0$
#593
b1111111 *
1$
#594
0$
#595
b11 )
b11111110 *
1$
#596
0$
#597
b11111101 *
1$
#598
0$
#599
b11111110 )
b11111011 *
b11 #
1$
#600
0$
#601
b11 )
b11110111 *
1$
#602
0$
#603
b11101111 *
1$
#604
0$
#605
b11111111 )
b11011111 *
1$
#606
0$
#607
b10111111 *
1$
#608
0$
#609
b1111111 *
1$
#610
0$
#611
b11 )
b11111110 *
1$
#612
0$
#613
b11111101 *
1$
#614
0$
#615
b11111110 )
b11111011 *
1$
#616
0$
#617
b11 )
b11110111 *
1$
#618
0$
#619
b11101111 *
1$
#620
0$
#621
b11111111 )
b11011111 *
1$
#622
0$
#623
b10111111 *
1$
#624
0$
#625
b1111111 *
1$
#626
0$
#627
b11 )
b11111110 *
1$
#628
0$
#629
b11111101 *
1$
#630
0$
#631
b11111110 )
b11111011 *
1$
#632
0$
#633
b11 )
b11110111 *
1$
#634
0$
#635
b11101111 *
1$
#636
0$
#637
b11111111 )
b11011111 *
1$
#638
0$
#639
b10111111 *
1$
#640
0$
#641
b1111111 *
1$
#642
0$
#643
b11 )
b11111110 *
1$
#644
0$
#645
b11111101 *
1$
#646
0$
#647
b11111110 )
b11111011 *
1$
#648
0$
#649
b11 )
b11110111 *
1$
#650
0$
#651
b11101111 *
1$
#652
0$
#653
b11111111 )
b11011111 *
1$
#654
0$
#655
b10111111 *
1$
#656
0$
#657
b1111111 *
1$
#658
0$
#659
b11 )
b11111110 *
1$
#660
0$
#661
b11111101 *
1$
#662
0$
#663
b11111110 )
b11111011 *
1$
#664
0$
#665
b11 )
b11110111 *
1$
#666
0$
#667
b11101111 *
1$
#668
0$
#669
b11111111 )
b11011111 *
1$
#670
0$
#671
b10111111 *
1$
#672
0$
#673
b1111111 *
1$
#674
0$
#675
b11 )
b11111110 *
1$
#676
0$
#677
b11111101 *
1$
#678
0$
#679
b11111110 )
b11111011 *
1$
#680
0$
#681
b11 )
b11110111 *
1$
#682
0$
#683
b11101111 *
1$
#684
0$
#685
b11111111 )
b11011111 *
1$
#686
0$
#687
b10111111 *
1$
#688
0$
#689
b1111111 *
1$
#690
0$
#691
b11 )
b11111110 *
1$
#692
0$
#693
b11111101 *
1$
#694
0$
#695
b11111110 )
b11111011 *
1$
#696
0$
#697
b11 )
b11110111 *
1$
#698
0$
#699
b11101111 *
1$
#700
0$
#701
b11111111 )
b11011111 *
1$
#702
0$
#703
b10111111 *
1$
#704
0$
#705
b1111111 *
1$
#706
0$
#707
b11 )
b11111110 *
1$
#708
0$
#709
b11111101 *
1$
#710
0$
#711
b11111110 )
b11111011 *
1$
#712
0$
#713
b11 )
b11110111 *
1$
#714
0$
#715
b11101111 *
1$
#716
0$
#717
b11111111 )
b11011111 *
1$
#718
0$
#719
b10111111 *
1$
#720
0$
#721
b1111111 *
1$
#722
0$
#723
b11 )
b11111110 *
1$
#724
0$
#725
b11111101 *
1$
#726
0$
#727
b11111110 )
b11111011 *
1$
#728
0$
#729
b11 )
b11110111 *
1$
#730
0$
#731
b11101111 *
1$
#732
0$
#733
b11111111 )
b11011111 *
1$
#734
0$
#735
b10111111 *
1$
#736
0$
#737
b1111111 *
1$
#738
0$
#739
b11 )
b11111110 *
1$
#740
0$
#741
b11111101 *
1$
#742
0$
#743
b11111110 )
b11111011 *
1$
#744
0$
#745
b11 )
b11110111 *
1$
#746
0$
#747
b11101111 *
1$
#748
0$
#749
b11111111 )
b11011111 *
1$
#750
0$
#751
b10111111 *
1$
#752
0$
#753
b1111111 *
1$
#754
0$
#755
b11 )
b11111110 *
1$
#756
0$
#757
b11111101 *
1$
#758
0$
#759
b11111110 )
b11111011 *
1$
#760
0$
#761
b11 )
b11110111 *
1$
#762
0$
#763
b11101111 *
1$
#764
0$
#765
b11111111 )
b11011111 *
1$
#766
0$
#767
b10111111 *
1$
#768
0$
#769
b1111111 *
1$
#770
0$
#771
b11 )
b11111110 *
1$
#772
0$
#773
b11111101 *
1$
#774
0$
#775
b11111110 )
b11111011 *
1$
#776
0$
#777
b11 )
b11110111 *
1$
#778
0$
#779
b11101111 *
1$
#780
0$
#781
b11111111 )
b11011111 *
1$
#782
0$
#783
b10111111 *
1$
#784
0$
#785
b1111111 *
1$
#786
0$
#787
b11 )
b11111110 *
1$
#788
0$
#789
b11111101 *
1$
#790
0$
#791
b11111110 )
b11111011 *
1$
#792
0$
#793
b11 )
b11110111 *
1$
#794
0$
#795
b11101111 *
1$
#796
0$
#797
b11111111 )
b11011111 *
1$
#798
0$
#799
b10111111 *
b100 #
1$
#800
0$
#801
b1111111 *
1$
#802
0$
#803
b11 )
b11111110 *
1$
#804
0$
#805
b11111101 *
1$
#806
0$
#807
b11111110 )
b11111011 *
1$
#808
0$
#809
b11 )
b11110111 *
1$
#810
0$
#811
b11101111 *
1$
#812
0$
#813
b11111111 )
b11011111 *
1$
#814
0$
#815
b10111111 *
1$
#816
0$
#817
b1111111 *
1$
#818
0$
#819
b11 )
b11111110 *
1$
#820
0$
#821
b11111101 *
1$
#822
0$
#823
b11111110 )
b11111011 *
1$
#824
0$
#825
b11 )
b11110111 *
1$
#826
0$
#827
b11101111 *
1$
#828
0$
#829
b11111111 )
b11011111 *
1$
#830
0$
#831
b10111111 *
1$
#832
0$
#833
b1111111 *
1$
#834
0$
#835
b11 )
b11111110 *
1$
#836
0$
#837
b11111101 *
1$
#838
0$
#839
b11111110 )
b11111011 *
1$
#840
0$
#841
b11 )
b11110111 *
1$
#842
0$
#843
b11101111 *
1$
#844
0$
#845
b11111111 )
b11011111 *
1$
#846
0$
#847
b10111111 *
1$
#848
0$
#849
b1111111 *
1$
#850
0$
#851
b11 )
b11111110 *
1$
#852
0$
#853
b11111101 *
1$
#854
0$
#855
b11111110 )
b11111011 *
1$
#856
0$
#857
b11 )
b11110111 *
1$
#858
0$
#859
b11101111 *
1$
#860
0$
#861
b11111111 )
b11011111 *
1$
#862
0$
#863
b10111111 *
1$
#864
0$
#865
b1111111 *
1$
#866
0$
#867
b11 )
b11111110 *
1$
#868
0$
#869
b11111101 *
1$
#870
0$
#871
b11111110 )
b11111011 *
1$
#872
0$
#873
b11 )
b11110111 *
1$
#874
0$
#875
b11101111 *
1$
#876
0$
#877
b11111111 )
b11011111 *
1$
#878
0$
#879
b10111111 *
1$
#880
0$
#881
b1111111 *
1$
#882
0$
#883
b11 )
b11111110 *
1$
#884
0$
#885
b11111101 *
1$
#886
0$
#887
b11111110 )
b11111011 *
1$
#888
0$
#889
b11 )
b11110111 *
1$
#890
0$
#891
b11101111 *
1$
#892
0$
#893
b11111111 )
b11011111 *
1$
#894
0$
#895
b10111111 *
1$
#896
0$
#897
b1111111 *
1$
#898
0$
#899
b11 )
b11111110 *
1$
#900
0$
#901
b11111101 *
1$
#902
0$
#903
b11111110 )
b11111011 *
1$
#904
0$
#905
b11 )
b11110111 *
1$
#906
0$
#907
b11101111 *
1$
#908
0$
#909
b11111111 )
b11011111 *
1$
#910
0$
#911
b10111111 *
1$
#912
0$
#913
b1111111 *
1$
#914
0$
#915
b11 )
b11111110 *
1$
#916
0$
#917
b11111101 *
1$
#918
0$
#919
b11111110 )
b11111011 *
1$
#920
0$
#921
b11 )
b11110111 *
1$
#922
0$
#923
b11101111 *
1$
#924
0$
#925
b11111111 )
b11011111 *
1$
#926
0$
#927
b10111111 *
1$
#928
0$
#929
b1111111 *
1$
#930
0$
#931
b11 )
b11111110 *
1$
#932
0$
#933
b11111101 *
1$
#934
0$
#935
b11111110 )
b11111011 *
1$
#936
0$
#937
b11 )
b11110111 *
1$
#938
0$
#939
b11101111 *
1$
#940
0$
#941
b11111111 )
b11011111 *
1$
#942
0$
#943
b10111111 *
1$
#944
0$
#945
b1111111 *
1$
#946
0$
#947
b11 )
b11111110 *
1$
#948
0$
#949
b11111101 *
1$
#950
0$
#951
b11111110 )
b11111011 *
1$
#952
0$
#953
b11 )
b11110111 *
1$
#954
0$
#955
b11101111 *
1$
#956
0$
#957
b11111111 )
b11011111 *
1$
#958
0$
#959
b10111111 *
1$
#960
0$
#961
b1111111 *
1$
#962
0$
#963
b11 )
b11111110 *
1$
#964
0$
#965
b11111101 *
1$
#966
0$
#967
b11111110 )
b11111011 *
1$
#968
0$
#969
b11 )
b11110111 *
1$
#970
0$
#971
b11101111 *
1$
#972
0$
#973
b11111111 )
b11011111 *
1$
#974
0$
#975
b10111111 *
1$
#976
0$
#977
b1111111 *
1$
#978
0$
#979
b11 )
b11111110 *
1$
#980
0$
#981
b11111101 *
1$
#982
0$
#983
b11111110 )
b11111011 *
1$
#984
0$
#985
b11 )
b11110111 *
1$
#986
0$
#987
b11101111 *
1$
#988
0$
#989
b11111111 )
b11011111 *
1$
#990
0$
#991
b10111111 *
1$
#992
0$
#993
b1111111 *
1$
#994
0$
#995
b11 )
b11111110 *
1$
#996
0$
#997
b11111101 *
1$
#998
0$
#999
b11111110 )
b11111011 *
b101 #
1$
#1000
0$
#1001
b11 )
b11110111 *
1$
#1002
0$
1&
#1003
b11101111 *
1$
#1004
0$
#1005
b11111111 )
b11011111 *
1$
#1006
0$
#1007
b10111111 *
1$
#1008
0$
#1009
b1111111 *
1$
#1010
0$
#1011
b11 )
b11111110 *
1$
#1012
0$
#1013
b11111101 *
1$
#1014
0$
#1015
b11111110 )
b11111011 *
1$
#1016
0$
#1017
b11 )
b11110111 *
1$
#1018
0$
#1019
b11101111 *
1$
#1020
0$
#1021
b11111111 )
b11011111 *
1$
#1022
0$
#1023
b10111111 *
1$
#1024
0$
#1025
b1111111 *
1$
#1026
0$
#1027
b11 )
b11111110 *
1$
#1028
0$
#1029
b11111101 *
1$
#1030
0$
#1031
b11111110 )
b11111011 *
1$
#1032
0$
#1033
b11 )
b11110111 *
1$
#1034
0$
#1035
b11101111 *
1$
#1036
0$
#1037
b11111111 )
b11011111 *
1$
#1038
0$
#1039
b10111111 *
1$
#1040
0$
#1041
b1111111 *
b1 "
1$
#1042
0$
#1043
b10011111 )
b11111110 *
1$
#1044
0$
#1045
b11 )
b11111101 *
1$
#1046
0$
#1047
b11111110 )
b11111011 *
1$
#1048
0$
#1049
b11 )
b11110111 *
1$
#1050
0$
#1051
b11101111 *
1$
